squidly/__init__.py
squidly/__main__.py
squidly/blast.py
squidly/download_models_hf.py
squidly/squidly.py
squidly/squidly_single_model.py
squidly-0.1.0.data/data/LICENSE
squidly-0.1.0.dist-info/licenses/LICENSE
squidly-0.1.0.dist-info/METADATA
squidly-0.1.0.dist-info/WHEEL
squidly-0.1.0.dist-info/entry_points.txt
squidly-0.1.0.dist-info/top_level.txt
squidly-0.1.0.dist-info/RECORD
