Metadata-Version: 2.4
Name: squidly
Version: 0.1.0
Home-page: https://github.com/WRiegs/Squidly
Author: William Reiger
Author-email: w.rieger@uq.edu.au
License: GPL3
Project-URL: Bug Tracker, https://github.com/WRiegs/Squidly/issues
Project-URL: Documentation, https://github.com/WRiegs/Squidly
Project-URL: Source Code, https://github.com/WRiegs/Squidly
Keywords: gene-annotation,bioinformatics,catalytic-site-prediction
Classifier: Intended Audience :: Science/Research
Classifier: License :: OSI Approved :: GNU General Public License v3 (GPLv3)
Classifier: Natural Language :: English
Classifier: Operating System :: OS Independent
Classifier: Programming Language :: Python :: 3.6
Classifier: Programming Language :: Python :: 3.7
Classifier: Programming Language :: Python :: 3.8
Classifier: Topic :: Scientific/Engineering :: Bio-Informatics
Requires-Python: >=3.10
License-File: LICENSE
Requires-Dist: pandas>=2.1.4
Requires-Dist: numpy>=1.22.4
Requires-Dist: fair-esm
Requires-Dist: typer
Requires-Dist: psutil
Requires-Dist: biopython
Requires-Dist: sciutil
Requires-Dist: tqdm
Requires-Dist: enzymetk
Requires-Dist: huggingface_hub
Dynamic: author
Dynamic: author-email
Dynamic: classifier
Dynamic: description
Dynamic: description-content-type
Dynamic: home-page
Dynamic: keywords
Dynamic: license
Dynamic: license-file
Dynamic: project-url
Dynamic: requires-dist
Dynamic: requires-python
